huaweicloudsdkaos/__init__.py
huaweicloudsdkaos/v1/__init__.py
huaweicloudsdkaos/v1/aos_async_client.py
huaweicloudsdkaos/v1/aos_client.py
huaweicloudsdkaos/v1/model/__init__.py
huaweicloudsdkaos/v1/model/administration_agency_name_primitive_type_holder.py
huaweicloudsdkaos/v1/model/administration_agency_urn_primitive_type_holder.py
huaweicloudsdkaos/v1/model/agencies_primitive_type_holder.py
huaweicloudsdkaos/v1/model/agency.py
huaweicloudsdkaos/v1/model/apply_execution_plan_request.py
huaweicloudsdkaos/v1/model/apply_execution_plan_request_body.py
huaweicloudsdkaos/v1/model/apply_execution_plan_response.py
huaweicloudsdkaos/v1/model/base_template.py
huaweicloudsdkaos/v1/model/base_template_body.py
huaweicloudsdkaos/v1/model/base_template_version.py
huaweicloudsdkaos/v1/model/call_identity_primitive_type_holder.py
huaweicloudsdkaos/v1/model/configuration_primitive_type_holder.py
huaweicloudsdkaos/v1/model/configuration_primitive_type_holder_configuration.py
huaweicloudsdkaos/v1/model/continue_deploy_stack_request.py
huaweicloudsdkaos/v1/model/continue_deploy_stack_request_body.py
huaweicloudsdkaos/v1/model/continue_deploy_stack_response.py
huaweicloudsdkaos/v1/model/continue_rollback_stack_request.py
huaweicloudsdkaos/v1/model/continue_rollback_stack_request_body.py
huaweicloudsdkaos/v1/model/continue_rollback_stack_response.py
huaweicloudsdkaos/v1/model/create_execution_plan_request.py
huaweicloudsdkaos/v1/model/create_execution_plan_request_body.py
huaweicloudsdkaos/v1/model/create_execution_plan_response.py
huaweicloudsdkaos/v1/model/create_private_hook_request.py
huaweicloudsdkaos/v1/model/create_private_hook_request_body.py
huaweicloudsdkaos/v1/model/create_private_hook_response.py
huaweicloudsdkaos/v1/model/create_private_hook_version_request.py
huaweicloudsdkaos/v1/model/create_private_hook_version_request_body.py
huaweicloudsdkaos/v1/model/create_private_hook_version_response.py
huaweicloudsdkaos/v1/model/create_private_module_request.py
huaweicloudsdkaos-3.1.184.dist-info/METADATA
huaweicloudsdkaos-3.1.184.dist-info/WHEEL
huaweicloudsdkaos-3.1.184.dist-info/licenses/LICENSE
huaweicloudsdkaos-3.1.184.dist-info/RECORD
